fortress_sdk_python/__init__.py
fortress_sdk_python/client.py
fortress_sdk_python/crypto.py
fortress_sdk_python/database.py
fortress_sdk_python/fortress.py
fortress_sdk_python/postgres.py
fortress_sdk_python-0.1.16.dist-info/LICENSE
fortress_sdk_python-0.1.16.dist-info/METADATA
fortress_sdk_python-0.1.16.dist-info/WHEEL
fortress_sdk_python-0.1.16.dist-info/RECORD
