Metadata-Version: 2.1
Name: fortress-sdk-python
Version: 0.1.16
Summary: Fortress Platform Python API SDK
Author: Fortress
Author-email: founders@fortress.build
Requires-Python: >=3.11,<4.0
Classifier: Programming Language :: Python :: 3
Classifier: Programming Language :: Python :: 3.11
Classifier: Programming Language :: Python :: 3.12
Requires-Dist: cryptography (>=43.0.0,<44.0.0)
Requires-Dist: psycopg2 (>=2.9.9,<3.0.0)
Requires-Dist: requests (>=2.32.3,<3.0.0)
